tuze_sdk/__init__.py
tuze_sdk/http_util.py
tuze_sdk-1.5.0.dist-info/METADATA
tuze_sdk-1.5.0.dist-info/WHEEL
tuze_sdk-1.5.0.dist-info/top_level.txt
tuze_sdk-1.5.0.dist-info/RECORD
